maggeo/__init__.py
maggeo/auxiliaryfunctions.py
maggeo/chaos.py
maggeo/cli.py
maggeo/core.py
maggeo/date_utils.py
maggeo/debug.py
maggeo/debug_config.py
maggeo/gps.py
maggeo/indices.py
maggeo/interpolation.py
maggeo/parallel_processing.py
maggeo/row_handler.py
maggeo/swarm.py
maggeo/swarm_data_manager.py
maggeo-0.2.1.dist-info/licenses/LICENSE
maggeo-0.2.1.dist-info/METADATA
maggeo-0.2.1.dist-info/WHEEL
maggeo-0.2.1.dist-info/entry_points.txt
maggeo-0.2.1.dist-info/top_level.txt
maggeo-0.2.1.dist-info/RECORD
