Metadata-Version: 2.4
Name: maggeo
Version: 0.2.1
Summary: Annotate GPS trajectories with geomagnetic data from ESA Swarm satellites.
Home-page: https://github.com/MagGeo/MagGeo-Annotation-Program
Author: Fernando Benitez-Paez, Urška Demšar, Jed Long, Ciaran Beggan
Author-email: Fernando Benitez-Paez <Fernando.Benitez@st-andrews.ac.uk>, Urška Demšar <ud2@st-andrews.ac.uk>, Jed Long <jed.long@uwo.ca>, Ciaran Beggan <ciar@bgs.ac.uk>
Maintainer-email: Fernando Benitez-Paez <Fernando.Benitez@st-andrews.ac.uk>
License: MIT
Project-URL: homepage, https://github.com/MagGeo/MagGeo
Project-URL: repository, https://github.com/MagGeo/MagGeo
Project-URL: documentation, https://maggeo.github.io/MagGeo/
Keywords: data fusion,GPS,Swarm,annotation,Earth's magnetic field,Ecology
Classifier: Development Status :: 4 - Beta
Classifier: Intended Audience :: Science/Research
Classifier: Programming Language :: Python :: 3
Classifier: Programming Language :: Python :: 3.8
Classifier: Programming Language :: Python :: 3.9
Classifier: Programming Language :: Python :: 3.10
Classifier: Programming Language :: Python :: 3.11
Classifier: License :: OSI Approved :: MIT License
Classifier: Operating System :: OS Independent
Classifier: Topic :: Scientific/Engineering
Classifier: Topic :: Scientific/Engineering :: GIS
Classifier: Topic :: Scientific/Engineering :: Physics
Classifier: Topic :: Scientific/Engineering :: Information Analysis
Requires-Python: >=3.8
License-File: LICENSE
Requires-Dist: numpy>=1.21.0
Requires-Dist: scipy>=1.7.0
Requires-Dist: pandas>=1.3.0
Requires-Dist: matplotlib>=3.4.0
Requires-Dist: jinja2>=3.0.0
Requires-Dist: tqdm>=4.60.0
Requires-Dist: click>=8.0.0
Requires-Dist: pyyaml>=5.4.0
Requires-Dist: viresclient>=0.11.0
Requires-Dist: chaosmagpy>=0.11.0
Requires-Dist: requests>=2.25.0
Requires-Dist: pooch>=1.3.0
Provides-Extra: dev
Requires-Dist: pytest>=6.0.0; extra == "dev"
Requires-Dist: pytest-cov>=2.12.0; extra == "dev"
Requires-Dist: black>=21.0.0; extra == "dev"
Requires-Dist: flake8>=3.9.0; extra == "dev"
Requires-Dist: mypy>=0.910; extra == "dev"
Provides-Extra: notebooks
Requires-Dist: jupyter>=1.0.0; extra == "notebooks"
Requires-Dist: jupyterlab>=3.0.0; extra == "notebooks"
Requires-Dist: ipywidgets>=7.6.0; extra == "notebooks"
Provides-Extra: geo
Requires-Dist: cartopy>=0.19.0; extra == "geo"
Requires-Dist: geopandas>=0.9.0; extra == "geo"
Requires-Dist: xarray>=0.18.0; extra == "geo"
Requires-Dist: netcdf4>=1.5.0; extra == "geo"
Provides-Extra: docs
Requires-Dist: mkdocs>=1.5.0; extra == "docs"
Requires-Dist: mkdocs-material>=9.4.0; extra == "docs"
Requires-Dist: mkdocstrings[python]>=0.24.0; extra == "docs"
Requires-Dist: mkdocs-jupyter>=0.24.0; extra == "docs"
Requires-Dist: mkdocs-git-revision-date-localized-plugin>=1.2.0; extra == "docs"
Requires-Dist: mkdocs-awesome-pages-plugin>=2.9.0; extra == "docs"
Dynamic: author
Dynamic: home-page
Dynamic: license-file
Dynamic: requires-python
